eris/__init__.py
eris/_core.py
eris/_errors.py
eris/_result.py
eris/py.typed
bolton_eris-0.2.3.dist-info/METADATA
bolton_eris-0.2.3.dist-info/WHEEL
bolton_eris-0.2.3.dist-info/top_level.txt
bolton_eris-0.2.3.dist-info/RECORD
