Metadata-Version: 2.1
Name: bolton-eris
Version: 0.2.3
Summary: The Greek Goddess of Strife and Discord... A better way to handle, trace, and log errors in Python.
Home-page: https://github.com/python-boltons/eris
Author: Bryan M Bugyi
Author-email: bryanbugyi34@gmail.com
License: MIT license
Platform: UNKNOWN
Classifier: Development Status :: 3 - Alpha
Classifier: Intended Audience :: Developers
Classifier: License :: OSI Approved :: MIT License
Classifier: Natural Language :: English
Classifier: Programming Language :: Python :: 3
Classifier: Programming Language :: Python :: 3.8
Classifier: Programming Language :: Python :: 3.9
Classifier: Programming Language :: Python :: 3.10
Requires-Python: >=3.8
Requires-Dist: bolton-ion (~=0.1.0)
Requires-Dist: bolton-metaman (~=0.1.1)
Requires-Dist: bolton-typist (~=0.2.0)
